python_libphash-1.1.0.dist-info/WHEEL
python_libphash-1.1.0.dist-info/top_level.txt
python_libphash-1.1.0.dist-info/METADATA
python_libphash-1.1.0.dist-info/RECORD
python_libphash-1.1.0.dist-info/licenses/LICENSE
libphash/context.py
libphash/utils.py
libphash/_build.py
libphash/types.py
libphash/_native.pyi
libphash/_native.abi3.so
libphash/exceptions.py
libphash/py.typed
libphash/__init__.py
