Metadata-Version: 2.4
Name: python-libphash
Version: 1.1.0
Summary: High-performance perceptual hashing library (CFFI bindings)
Author-email: gudoshnikovn <gudoshnikov-na@yandex.ru>
License-Expression: MIT
Project-URL: Homepage, https://github.com/gudoshnikovn/python-libphash
Classifier: Programming Language :: Python :: 3
Classifier: Programming Language :: C
Classifier: Topic :: Multimedia :: Graphics
Requires-Python: >=3.8
License-File: LICENSE
Requires-Dist: cffi>=1.15.0
Provides-Extra: dev
Requires-Dist: pytest; extra == "dev"
Requires-Dist: mypy; extra == "dev"
Requires-Dist: ruff; extra == "dev"
Dynamic: license-file
